calchasai/__init__.py
calchasai/_coins/__init__.py
calchasai/_coins/binance.py
calchasai/_coins/bitstamp.py
calchasai/_coins/coins.py
calchasai/data_service/__init__.py
calchasai/data_service/db.py
calchasai/data_service/preprocess.py
calchasai/data_service/queries.py
calchasai/data_service/test_conn.py
calchasai/downloader/__init__.py
calchasai/downloader/base_downloader.py
calchasai/downloader/binance.py
calchasai/downloader/bitstamp.py
calchasai/downloader/utils.py
calchasai/preproccess/__init__.py
calchasai/preproccess/csv_reader.py
calchasai/preproccess/stacked.py
calchasai/preproccess/utils.py
calchasai-0.0.1.dist-info/METADATA
calchasai-0.0.1.dist-info/WHEEL
calchasai-0.0.1.dist-info/top_level.txt
calchasai-0.0.1.dist-info/RECORD
