Metadata-Version: 2.1
Name: calchasai
Version: 0.0.1
Summary: A short description of your package
Author: ktz
Author-email: your.email@example.com
Classifier: Programming Language :: Python :: 3
Classifier: License :: OSI Approved :: MIT License
Classifier: Operating System :: OS Independent
Requires-Python: >=3.6
Requires-Dist: numpy
Requires-Dist: pandas
Requires-Dist: matplotlib
Requires-Dist: python-binance
Requires-Dist: psycopg2-binary
Requires-Dist: polars
